README.txt
setup.py
docs/HISTORY.txt
docs/LICENSE.GPL
docs/LICENSE.txt
plone/__init__.py
plone.app.protect.egg-info/PKG-INFO
plone.app.protect.egg-info/SOURCES.txt
plone.app.protect.egg-info/dependency_links.txt
plone.app.protect.egg-info/namespace_packages.txt
plone.app.protect.egg-info/not-zip-safe
plone.app.protect.egg-info/requires.txt
plone.app.protect.egg-info/top_level.txt
plone/app/__init__.py
plone/app/protect/__init__.py
plone/app/protect/authenticator.py
plone/app/protect/configure.zcml
plone/app/protect/interfaces.py
plone/app/protect/postonly.py
plone/app/protect/utils.py
plone/app/protect/version.txt
plone/app/protect/profiles/default/componentregistry.xml
plone/app/protect/profiles/default/metadata.xml
plone/app/protect/tests/__init__.py
plone/app/protect/tests/case.py
plone/app/protect/tests/testAuthenticator.py
plone/app/protect/tests/testPostOnly.py
