Metadata-Version: 1.0
Name: plone.app.protect
Version: 1.0b1
Summary: Security for browser forms
Home-page: http://svn.plone.org/svn/plone/plone.app.protect
Author: Wichert Akkerman
Author-email: plone-developers@lists.sourceforge.net
License: GPL
Keywords: plone security CSFS
Platform: UNKNOWN
Classifier: Framework :: Plone
Classifier: Framework :: Zope2
Classifier: Framework :: Zope3
Classifier: Programming Language :: Python
Classifier: Topic :: Software Development :: Libraries :: Python Modules
